{
  "$schema": "http://json.schemastore.org/sarif-1.0.0",
  "version": "1.0.0",
  "runs": [
    {
      "tool": {
        "name": "Microsoft (R) Visual C# Compiler",
        "version": "4.9.0.0",
        "fileVersion": "4.9.0-3.24067.18 (4fc721bb)",
        "semanticVersion": "4.9.0",
        "language": "en"
      },
      "results": [
        {
          "ruleId": "S107",
          "level": "warning",
          "message": "Constructor has 8 parameters, which is greater than the 7 authorized.",
          "locations": [
            {
              "resultFile": {
                "uri": "file:///Users/hosseinvahidazari/Projects/GitHub/VisualAccess/visualaccess.backend/src/VisualAccess.API/Controllers/ManageAccountController.cs",
                "region": {
                  "startLine": 33,
                  "startColumn": 39,
                  "endLine": 33,
                  "endColumn": 295
                }
              }
            }
          ],
          "properties": {
            "warningLevel": 1
          }
        },
        {
          "ruleId": "S107",
          "level": "warning",
          "message": "Constructor has 9 parameters, which is greater than the 7 authorized.",
          "locations": [
            {
              "resultFile": {
                "uri": "file:///Users/hosseinvahidazari/Projects/GitHub/VisualAccess/visualaccess.backend/src/VisualAccess.API/Controllers/RequestRoomPermissionController.cs",
                "region": {
                  "startLine": 36,
                  "startColumn": 47,
                  "endLine": 36,
                  "endColumn": 417
                }
              }
            }
          ],
          "properties": {
            "warningLevel": 1
          }
        },
        {
          "ruleId": "S5122",
          "level": "warning",
          "message": "Make sure this permissive CORS policy is safe here.",
          "locations": [
            {
              "resultFile": {
                "uri": "file:///Users/hosseinvahidazari/Projects/GitHub/VisualAccess/visualaccess.backend/src/VisualAccess.API/ConfigServices.cs",
                "region": {
                  "startLine": 33,
                  "startColumn": 21,
                  "endLine": 33,
                  "endColumn": 45
                }
              }
            }
          ],
          "properties": {
            "warningLevel": 1
          }
        }
      ],
      "rules": {
        "S107": {
          "id": "S107",
          "shortDescription": "Methods should not have too many parameters",
          "fullDescription": "Methods with a long parameter list are difficult to use, as maintainers must figure out the role of each parameter and keep track of their position.",
          "defaultLevel": "warning",
          "helpUri": "https://rules.sonarsource.com/csharp/RSPEC-107",
          "properties": {
            "category": "Major Code Smell",
            "isEnabledByDefault": false,
            "tags": [
              "C#",
              "MainSourceScope",
              "TestSourceScope",
              "SonarWay"
            ]
          }
        },
        "S5122": {
          "id": "S5122",
          "shortDescription": "Having a permissive Cross-Origin Resource Sharing policy is security-sensitive",
          "fullDescription": "Having a permissive Cross-Origin Resource Sharing policy is security-sensitive. It has led in the past to the following vulnerabilities:",
          "defaultLevel": "warning",
          "helpUri": "https://rules.sonarsource.com/csharp/RSPEC-5122",
          "properties": {
            "category": "Minor Security Hotspot",
            "isEnabledByDefault": true,
            "tags": [
              "C#",
              "MainSourceScope",
              "SonarWay"
            ]
          }
        }
      }
    }
  ]
}